vaa-0.2.1.dist-info/dependency_links.txt
vaa-0.2.1.dist-info/entry_points.txt
vaa-0.2.1.dist-info/METADATA
vaa-0.2.1.dist-info/top_level.txt
vaa-0.2.1.dist-info/WHEEL
vaa/_cached_property.py
vaa/_internal.py
vaa/_django_utils.py
vaa/_error.py
vaa/_auto.py
vaa/_aliases.py
vaa/__init__.py
vaa/_external.py
vaa-0.2.1.dist-info/LICENSE
vaa-0.2.1.dist-info/RECORD