Metadata-Version: 2.1
Name: vaa
Version: 0.2.1
Summary: Validators Adapter. The common interface for all validators.
Project-URL: Homepage, https://github.com/life4/vaa
Author: Gram Orsinium
Author-email: master_fess@mail.ru
Classifier: Development Status :: 5 - Production/Stable
Classifier: Environment :: Console
Classifier: Intended Audience :: Developers
Classifier: License :: OSI Approved :: MIT License
Classifier: Programming Language :: Python :: 3.5
Classifier: Programming Language :: Python :: 3.6
Classifier: Programming Language :: Python :: 3.7
Classifier: Programming Language :: Python :: 3
Classifier: Programming Language :: Python
Classifier: Topic :: Software Development :: Libraries :: Python Modules
Requires-Dist: cerberus; extra == "validators"
Requires-Dist: django; extra == "validators"
Requires-Dist: djangorestframework; extra == "validators"
Requires-Dist: marshmallow>=3.0.1; extra == "validators"
Requires-Dist: pyschemes; extra == "validators"
Requires-Dist: pytest; extra == "tests"
Requires-Dist: wtforms; extra == "validators"
Provides-Extra: tests
Provides-Extra: validators
